ccd/__init__.py
ccd/base.py
ccd/ephemeris.py
CCD-0.2.dist-info/LICENSE
CCD-0.2.dist-info/METADATA
CCD-0.2.dist-info/WHEEL
CCD-0.2.dist-info/top_level.txt
CCD-0.2.dist-info/RECORD
