Metadata-Version: 2.1
Name: CCD
Version: 0.2
Summary: A Python package about Chinese Lunisolar Calendar.
Home-page: https://github.com/aixcyi/CCD
Author: aixcyi
Author-email: 75880483+aixcyi@users.noreply.github.com
License: MIT
Project-URL: Source, https://github.com/aixcyi/CCD
Project-URL: Tracker, https://github.com/aixcyi/CCD/issues
Keywords: date,calendar,lunisolar,datetime,chinese,time
Classifier: Programming Language :: Python :: 3
Classifier: Programming Language :: Python :: 3.11
Classifier: Operating System :: OS Independent
Classifier: Natural Language :: Chinese (Simplified)
Classifier: License :: OSI Approved :: MIT License
Classifier: Topic :: Utilities
Requires-Python: >=3.11
License-File: LICENSE
